{
  "sections": [
    {
      "id": "hero-1",
      "component": "HeroBanner",
      "props": {
        "title": "Bem-vindo à Nossa Loja",
        "subtitle": "Os melhores produtos você encontra aqui",
        "buttonText": "Ver Produtos"
      }
    },
    {
      "id": "products-1",
      "component": "ProductGrid",
      "props": {
        "title": "Produtos em Destaque",
        "columns": 3,
        "products": [
          {
            "id": 1,
            "name": "Produto 1",
            "price": 99.9,
            "image": "https://via.placeholder.com/300"
          },
          {
            "id": 2,
            "name": "Produto 2",
            "price": 109.9,
            "image": "https://via.placeholder.com/300"
          },
          {
            "id": 3,
            "name": "Produto 3",
            "price": 119.9,
            "image": "https://via.placeholder.com/300"
          },
          {
            "id": 4,
            "name": "Produto 4",
            "price": 129.9,
            "image": "https://via.placeholder.com/300"
          },
          {
            "id": 5,
            "name": "Produto 5",
            "price": 139.9,
            "image": "https://via.placeholder.com/300"
          },
          {
            "id": 6,
            "name": "Produto 6",
            "price": 149.9,
            "image": "https://via.placeholder.com/300"
          },
          {
            "id": 7,
            "name": "Produto 7",
            "price": 159.9,
            "image": "https://via.placeholder.com/300"
          },
          {
            "id": 8,
            "name": "Produto 8",
            "price": 169.9,
            "image": "https://via.placeholder.com/300"
          },
          {
            "id": 9,
            "name": "Produto 9",
            "price": 179.9,
            "image": "https://via.placeholder.com/300"
          },
          {
            "id": 10,
            "name": "Produto 10",
            "price": 189.9,
            "image": "https://via.placeholder.com/300"
          },
          {
            "id": 11,
            "name": "Produto 11",
            "price": 199.9,
            "image": "https://via.placeholder.com/300"
          },
          {
            "id": 12,
            "name": "Produto 12",
            "price": 209.9,
            "image": "https://via.placeholder.com/300"
          }
        ]
      }
    },
    {
      "id": "hero-2",
      "component": "HeroBanner",
      "props": {
        "title": "Ofertas Especiais",
        "subtitle": "Até 50% de desconto",
        "buttonText": "Aproveitar"
      }
    }
  ]
}
